tree_sitter_vhdl/__init__.py
tree_sitter_vhdl/__init__.pyi
tree_sitter_vhdl/_binding.pyd
tree_sitter_vhdl/binding.c
tree_sitter_vhdl/py.typed
tree_sitter_vhdl/queries/Helix/highlights.scm
tree_sitter_vhdl/queries/Neovim/context.scm
tree_sitter_vhdl/queries/Neovim/folds.scm
tree_sitter_vhdl/queries/Neovim/highlights.scm
tree_sitter_vhdl/queries/Neovim/injections.scm
tree_sitter_vhdl/queries/Neovim/textobjects.scm
tree_sitter_vhdl-1.3.1.dist-info/licenses/License.md
tree_sitter_vhdl-1.3.1.dist-info/METADATA
tree_sitter_vhdl-1.3.1.dist-info/WHEEL
tree_sitter_vhdl-1.3.1.dist-info/top_level.txt
tree_sitter_vhdl-1.3.1.dist-info/RECORD
